pengbot/__init__.py
pengbot/context.py
pengbot/log.py
pengbot/main.py
pengbot/matchers.py
pengbot/utils.py
pengbot/adapters/__init__.py
pengbot/adapters/base.py
pengbot/adapters/shell.py
pengbot/adapters/slack.py
pengbot-0.1a1.dist-info/DESCRIPTION.rst
pengbot-0.1a1.dist-info/METADATA
pengbot-0.1a1.dist-info/RECORD
pengbot-0.1a1.dist-info/WHEEL
pengbot-0.1a1.dist-info/entry_points.txt
pengbot-0.1a1.dist-info/metadata.json
pengbot-0.1a1.dist-info/top_level.txt
