Metadata-Version: 2.0
Name: pengbot
Version: 0.1a1
Summary: A Bot framework to build bots with human manners
Home-page: https://github.com/mariocesar/pengbot
Author: Mario César Señoranis Ayala
Author-email: mariocesar.c50@gmail.com
License: UNKNOWN
Platform: UNKNOWN
Classifier: License :: OSI Approved :: MIT License
Classifier: Intended Audience :: Developers
Classifier: Programming Language :: Python :: 3
Classifier: Programming Language :: Python :: 3.3
Classifier: Programming Language :: Python :: 3.4
Classifier: Programming Language :: Python :: 3.5
Classifier: Operating System :: POSIX
Classifier: Operating System :: MacOS :: MacOS X
Classifier: Development Status :: 2 - Pre-Alpha
